.editorconfig
LICENSE.md
MANIFEST.in
Makefile
README.md
build_doc
download_cosp
pyproject.toml
setup.py
alcf/__init__.py
alcf/misc.py
alcf.egg-info/PKG-INFO
alcf.egg-info/SOURCES.txt
alcf.egg-info/dependency_links.txt
alcf.egg-info/entry_points.txt
alcf.egg-info/not-zip-safe
alcf.egg-info/requires.txt
alcf.egg-info/top_level.txt
alcf/algorithms/__init__.py
alcf/algorithms/couple.py
alcf/algorithms/lidar_ratio.py
alcf/algorithms/output_sample.py
alcf/algorithms/stats.py
alcf/algorithms/tsample.py
alcf/algorithms/zsample.py
alcf/algorithms/calibration/__init__.py
alcf/algorithms/calibration/default.py
alcf/algorithms/cloud_base_detection/__init__.py
alcf/algorithms/cloud_base_detection/default.py
alcf/algorithms/cloud_detection/__init__.py
alcf/algorithms/cloud_detection/default.py
alcf/algorithms/interp/__init__.py
alcf/algorithms/interp/area_block.pyx
alcf/algorithms/interp/area_linear.pyx
alcf/algorithms/interp/linear.py
alcf/algorithms/noise_removal/__init__.py
alcf/algorithms/noise_removal/default.py
alcf/bin/__init__.py
alcf/bin/alcf.py
alcf/cmds/__init__.py
alcf/cmds/auto.py
alcf/cmds/calibrate.py
alcf/cmds/compare.py
alcf/cmds/convert.py
alcf/cmds/download.py
alcf/cmds/lidar.py
alcf/cmds/main.py
alcf/cmds/model.py
alcf/cmds/plot.py
alcf/cmds/simulate.py
alcf/cmds/stats.py
alcf/cmds/auto_cmds/__init__.py
alcf/cmds/auto_cmds/compare.py
alcf/cmds/auto_cmds/lidar.py
alcf/cmds/auto_cmds/model.py
alcf/download/__init__.py
alcf/download/era5.py
alcf/download/merra2.py
alcf/fonts/LICENSE.md
alcf/fonts/PublicSans-Bold.otf
alcf/fonts/PublicSans-BoldItalic.otf
alcf/fonts/PublicSans-Italic.otf
alcf/fonts/PublicSans-Regular.otf
alcf/lidars/__init__.py
alcf/lidars/blview.py
alcf/lidars/caliop.py
alcf/lidars/chm15k.py
alcf/lidars/cl61.py
alcf/lidars/cloudnet.py
alcf/lidars/default.py
alcf/lidars/mpl.py
alcf/lidars/mpl2nc.py
alcf/lidars/vaisala.py
alcf/models/__init__.py
alcf/models/amps.py
alcf/models/cmip5.py
alcf/models/era5.py
alcf/models/icon.py
alcf/models/icon_intake_healpix.py
alcf/models/jra55.py
alcf/models/merra2.py
alcf/models/nzcsm.py
alcf/models/nzesm.py
alcf/models/um.py
cosp/.editorconfig
cosp/Makefile
cosp/Makefile.cmor1
cosp/Makefile.ibm
