Metadata-Version: 2.1
Name: alcf
Version: 2.3.1
Summary: Automatic Lidar and Ceilometer Framework (ALCF)
Home-page: https://alcf.peterkuma.net
Author: Peter Kuma, Adrian J. McDonald, Olaf Morgenstern, Richard Querel, Israel Silber, Connor J. Flynn
Author-email: peter@peterkuma.net
License: MIT
Keywords: alc,ceilometer,lidar,atmosphere,model,simulator,nwp,gcm,cosp,actsim,vaisala,cl51,cl31,lufft,chm-15k,minimpl,amps,merra-2,um
Classifier: Development Status :: 5 - Production/Stable
Classifier: Environment :: Console
Classifier: Intended Audience :: Science/Research
Classifier: License :: OSI Approved :: MIT License
Classifier: Operating System :: POSIX
Classifier: Programming Language :: Python :: 3
Classifier: Programming Language :: Cython
Classifier: Programming Language :: Fortran
Classifier: Topic :: Scientific/Engineering :: Atmospheric Science
Classifier: Topic :: Scientific/Engineering :: Physics
Classifier: Topic :: Scientific/Engineering :: Visualization
License-File: LICENSE.md
